<?xml version="1.0" encoding="UTF-8"?>
<metadata xml:lang="en"><Esri><CreaDate>20180831</CreaDate><CreaTime>15345600</CreaTime><ArcGISFormat>1.0</ArcGISFormat><SyncOnce>TRUE</SyncOnce><DataProperties><lineage><Process ToolSource="c:\program files (x86)\arcgis\desktop10.5\ArcToolbox\Toolboxes\Spatial Analyst Tools.tbx\ZonalStatisticsAsTable" Date="20180831" Time="153321">ZonalStatisticsAsTable croz_selected_subcol_2014_v3_rast subcol croz_resample_TRI.tif Z:\Informatics\S031\analyses\aschmidt\subcol_var\GIS\croz\tables\croz_selected_tri DATA MEAN</Process></lineage></DataProperties></Esri></metadata>
